onnxmodel_utils/__init__.py
onnxmodel_utils/container.py
onnxmodel_utils/dtype.py
onnxmodel_utils/model.py
onnxmodel_utils/utils.py
onnxmodel_utils/version.py
onnxmodel_utils/transform/__init__.py
onnxmodel_utils/transform/base.py
onnxmodel_utils/transform/decompose_sln.py
onnxmodel_utils/transform/fuse_mulmatmul.py
onnxmodel_utils/transform/merge_matmul.py
onnxmodel_utils-0.0.12.dist-info/LICENSE
onnxmodel_utils-0.0.12.dist-info/METADATA
onnxmodel_utils-0.0.12.dist-info/WHEEL
onnxmodel_utils-0.0.12.dist-info/top_level.txt
onnxmodel_utils-0.0.12.dist-info/RECORD
