Metadata-Version: 2.1
Name: onnxmodel-utils
Version: 0.0.12
Summary: utils for working with onnx models
Home-page: https://github.com/atksh/onnxmodel-utils
Author: atksh
License: MIT License
Classifier: Programming Language :: Python :: 3.7
Requires-Python: >=3.7
License-File: LICENSE
Requires-Dist: onnxsim >=0.4.8
Requires-Dist: onnxruntime >=1.12.1
Requires-Dist: onnx >=1.12.0
Requires-Dist: numpy >=1.21.2
Requires-Dist: pandas >=1.3.3
Requires-Dist: tqdm >=4.62.3
